netbox_ged/__init__.py
netbox_ged/filtersets.py
netbox_ged/forms.py
netbox_ged/models.py
netbox_ged/navigation.py
netbox_ged/search.py
netbox_ged/tables.py
netbox_ged/template_content.py
netbox_ged/urls.py
netbox_ged/utils.py
netbox_ged/views.py
netbox_ged/api/__init__.py
netbox_ged/api/serializers.py
netbox_ged/api/urls.py
netbox_ged/api/views.py
netbox_ged/migrations/0001_initial.py
netbox_ged/migrations/__init__.py
netbox_ged/templates/netbox_ged/document.html
netbox_ged/templates/netbox_ged/document_include.html
netbox_ged/templates/netbox_ged/documenttype.html
netbox_ged-0.2.1.dist-info/LICENSE
netbox_ged-0.2.1.dist-info/METADATA
netbox_ged-0.2.1.dist-info/WHEEL
netbox_ged-0.2.1.dist-info/top_level.txt
netbox_ged-0.2.1.dist-info/RECORD
