Metadata-Version: 2.1
Name: netbox_ged
Version: 0.2.1
Summary: Manage documents in Netbox
Home-page: https://github.com/pelt10/netbox-ged
Author: Pelt10
Author-email: contact@lethiec.me
Keywords: netbox,netbox-plugin,plugin
License-File: LICENSE
